javaobj/__init__.py
javaobj/constants.py
javaobj/modifiedutf8.py
javaobj/utils.py
javaobj/v1/__init__.py
javaobj/v1/beans.py
javaobj/v1/core.py
javaobj/v1/marshaller.py
javaobj/v1/transformers.py
javaobj/v1/unmarshaller.py
javaobj/v2/__init__.py
javaobj/v2/api.py
javaobj/v2/beans.py
javaobj/v2/core.py
javaobj/v2/main.py
javaobj/v2/stream.py
javaobj/v2/transformers.py
javaobj_py3-0.4.4.dist-info/LICENSE
javaobj_py3-0.4.4.dist-info/METADATA
javaobj_py3-0.4.4.dist-info/WHEEL
javaobj_py3-0.4.4.dist-info/top_level.txt
javaobj_py3-0.4.4.dist-info/RECORD
