Metadata-Version: 2.1
Name: javaobj-py3
Version: 0.4.4
Summary: Module for serializing and de-serializing Java objects.
Home-page: https://github.com/tcalmant/python-javaobj
Author: Volodymyr Buell
Author-email: vbuell@gmail.com
Maintainer: Thomas Calmant
Maintainer-email: thomas.calmant@gmail.com
License: Apache License 2.0
Keywords: python java marshalling serialization
Classifier: Development Status :: 3 - Alpha
Classifier: License :: OSI Approved :: Apache Software License
Classifier: Operating System :: OS Independent
Classifier: Programming Language :: Python :: 2.7
Classifier: Programming Language :: Python :: 3.4
Classifier: Programming Language :: Python :: 3.5
Classifier: Programming Language :: Python :: 3.6
Classifier: Programming Language :: Python :: 3.7
Classifier: Programming Language :: Python :: 3.8
Classifier: Programming Language :: Python :: 3.9
Classifier: Programming Language :: Python :: 3.10
Classifier: Programming Language :: Python :: 3.11
Classifier: Programming Language :: Python :: 3.12
Classifier: Topic :: Software Development :: Libraries :: Python Modules
License-File: LICENSE
Requires-Dist: enum34; python_version <= "3.4"
Requires-Dist: typing; python_version <= "3.4"
